occuspytial-0.1.0.dist-info/RECORD
occuspytial-0.1.0.dist-info/METADATA
occuspytial-0.1.0.dist-info/WHEEL
occuspytial-0.1.0.dist-info/LICENSE
occuspytial/distributions.c
occuspytial/data.c
occuspytial/distributions.cpython-36m-x86_64-linux-gnu.so
occuspytial/data.cpython-36m-x86_64-linux-gnu.so
occuspytial/utils.py
occuspytial/posterior.py
occuspytial/distributions.pyx
occuspytial/data.pyx
occuspytial/chain.py
occuspytial/__init__.py
occuspytial/tests/test_version.py
occuspytial/tests/test_utils.py
occuspytial/tests/test_posterior.py
occuspytial/tests/test_distributions.py
occuspytial/tests/test_data.py
occuspytial/tests/test_chain.py
occuspytial/gibbs/state.py
occuspytial/gibbs/probit.py
occuspytial/gibbs/parallel.py
occuspytial/gibbs/logit.py
occuspytial/gibbs/base.py
occuspytial/gibbs/__init__.py
occuspytial/gibbs/tests/test_state.py
occuspytial/gibbs/tests/test_samplers.py
